akello/__init__.py
akello/app_configs.yaml
akello/main.py
akello/secrets.py
akello/settings.py
akello/api/__init__.py
akello/api/app/v1/__init__.py
akello/api/app/v1/api.py
akello/api/app/v1/endpoints/__init__.py
akello/api/app/v1/endpoints/registry.py
akello/api/app/v1/endpoints/reports.py
akello/api/app/v1/endpoints/user.py
akello/auth/__init__.py
akello/auth/provider.py
akello/auth/aws_cognito/README.md
akello/auth/aws_cognito/__init__.py
akello/auth/aws_cognito/auth_settings.py
akello/auth/aws_cognito/aws_cognito.py
akello/cli/.template.api.env
akello/cli/.template.env
akello/cli/__init__.py
akello/cli/akello.py
akello/cli/dev-build-single.sh
akello/cli/dev-setup-local.sh
akello/cli/docker-compose.yml
akello/cli/.cognito/config.json
akello/cli/.cognito/db/clients.json
akello/cli/.cognito/db/local_4yfGDg3h.json
akello/cli/commands/__init__.py
akello/cli/commands/analytics.py
akello/cli/commands/build.py
akello/cli/commands/prompt.py
akello/cli/commands/setup.py
akello/cli/commands/start.py
akello/cli/commands/mock/__init__.py
akello/cli/commands/mock/patient.py
akello/cli/commands/mock/registry.py
akello/cli/commands/mock/treatment_log.py
akello/cli/commands/mock/user.py
akello/db/__init__.py
akello/db/models.py
akello/db/types.py
akello/db/connector/__init__.py
akello/db/connector/dynamodb.py
akello/db/connector/s3.py
akello/decorators/__init__.py
akello/decorators/akello_plan_tier.py
akello/decorators/mixin.py
akello/fhir/__init__.py
akello/fhir/fhir.schema.json
akello/fhir/hl7/README.md
akello/fhir/hl7/__init__.py
akello/fhir/hl7/fhir_v6_models.py
akello/screeners/README.md
akello/screeners/__init__.py
akello/screeners/FHIR/phq9_fhir.json
akello/screeners/FHIR/phq9_response.json
akello/screeners/R4/__init__.py
akello/screeners/R4/gad7.R4.json
akello/screeners/R4/phq9.R4.json
akello/screeners/measurements/FHIR_weights.template
akello/screeners/measurements/api_weights.template
akello/screeners/measurements/survey_GAD-7.yaml
akello-0.0.24.dist-info/METADATA
akello-0.0.24.dist-info/WHEEL
akello-0.0.24.dist-info/entry_points.txt
akello-0.0.24.dist-info/licenses/LICENSE
akello-0.0.24.dist-info/RECORD
